aiohttp_rest_api/__init__.py
aiohttp_rest_api/__version__.py
aiohttp_rest_api/loader.py
aiohttp_rest_api/responses.py
aiohttp_rest_api/swagger.py
aiohttp_rest_api/swagger_ui/index.html
aiohttp_rest_api/swagger_ui/o2c.html
aiohttp_rest_api/swagger_ui/swagger-ui.js
aiohttp_rest_api/swagger_ui/css/print.css
aiohttp_rest_api/swagger_ui/css/reset.css
aiohttp_rest_api/swagger_ui/css/screen.css
aiohttp_rest_api/swagger_ui/css/style.css
aiohttp_rest_api/swagger_ui/css/typography.css
aiohttp_rest_api/swagger_ui/fonts/DroidSans-Bold.ttf
aiohttp_rest_api/swagger_ui/fonts/DroidSans.ttf
aiohttp_rest_api/swagger_ui/images/collapse.gif
aiohttp_rest_api/swagger_ui/images/expand.gif
aiohttp_rest_api/swagger_ui/images/explorer_icons.png
aiohttp_rest_api/swagger_ui/images/favicon-16x16.png
aiohttp_rest_api/swagger_ui/images/favicon-32x32.png
aiohttp_rest_api/swagger_ui/images/favicon.ico
aiohttp_rest_api/swagger_ui/images/logo_small.png
aiohttp_rest_api/swagger_ui/images/pet_store_api.png
aiohttp_rest_api/swagger_ui/images/throbber.gif
aiohttp_rest_api/swagger_ui/images/wordnik_api.png
aiohttp_rest_api/swagger_ui/lang/ca.js
aiohttp_rest_api/swagger_ui/lang/en.js
aiohttp_rest_api/swagger_ui/lang/es.js
aiohttp_rest_api/swagger_ui/lang/fr.js
aiohttp_rest_api/swagger_ui/lang/geo.js
aiohttp_rest_api/swagger_ui/lang/it.js
aiohttp_rest_api/swagger_ui/lang/ja.js
aiohttp_rest_api/swagger_ui/lang/ko-kr.js
aiohttp_rest_api/swagger_ui/lang/pl.js
aiohttp_rest_api/swagger_ui/lang/pt.js
aiohttp_rest_api/swagger_ui/lang/ru.js
aiohttp_rest_api/swagger_ui/lang/tr.js
aiohttp_rest_api/swagger_ui/lang/translator.js
aiohttp_rest_api/swagger_ui/lang/zh-cn.js
example/__init__.py
example/main.py
example/endpoints/__init__.py
example/endpoints/demo_endpoint.py
example/endpoints/demo_exception_endpoint.py
aiohttp_rest_api_fork-0.0.5.dist-info/LICENSE
aiohttp_rest_api_fork-0.0.5.dist-info/METADATA
aiohttp_rest_api_fork-0.0.5.dist-info/WHEEL
aiohttp_rest_api_fork-0.0.5.dist-info/top_level.txt
aiohttp_rest_api_fork-0.0.5.dist-info/RECORD
